safepay_python/__init__.py
safepay_python/safepay.py
safepay_python/resources/checkout.py
safepay_python/resources/payments.py
safepay_python/resources/verify.py
safepay_python/utils/builder.py
safepay_python/utils/constants.py
safepay_python/utils/secure_compare.py
safepay_python/utils/validation.py
safepay_python-0.0.6.dist-info/METADATA
safepay_python-0.0.6.dist-info/WHEEL
safepay_python-0.0.6.dist-info/licenses/LICENSE
safepay_python-0.0.6.dist-info/RECORD
