Metadata-Version: 2.1
Name: safepay_python
Version: 0.0.6
Summary: Safepay's python SDK for checkout integration
Project-URL: Homepage, https://github.com/getsafepay/safepay-python
Project-URL: Bug Tracker, https://github.com/getsafepay/safepay-python/issues
Author-email: Fatima Aurangzeb <faurangzeb@getsafepay.com>
License-File: LICENSE
Classifier: License :: OSI Approved :: MIT License
Classifier: Operating System :: OS Independent
Classifier: Programming Language :: Python :: 3
Requires-Python: >=3.6
Requires-Dist: requests==2.27.1
Requires-Dist: six==1.16.0
Requires-Dist: urllib3==1.26.14
